rask_njord_uprofile
