Metadata-Version: 1.0
Name: rask-njord-uprofile
Version: 0.0.41
Summary: Rask Uprofile Connector
Home-page: https://gitlab.com/vikingmakt/rask_njord_uprofile
Author: Umgeher Torgersen
Author-email: me@umgeher.org
License: https://gitlab.com/vikingmakt/rask_njord_uprofile/raw/master/LICENSE
Platform: UNKNOWN
